lfapi/__init__.py
lfapi/_version.py
lfapi/auth.py
lfapi/client.py
lfapi/dep_utils.py
lfapi/errors.py
lfapi/http_utils.py
lfapi/models.py
lfapi-0.10.0.dist-info/LICENSE.md
lfapi-0.10.0.dist-info/METADATA
lfapi-0.10.0.dist-info/WHEEL
lfapi-0.10.0.dist-info/top_level.txt
lfapi-0.10.0.dist-info/RECORD
