Metadata-Version: 2.1
Name: lfapi
Version: 0.10.0
Summary: The Python library for the ListenFirst API
Home-page: https://github.com/ListenFirstMedia/lf-python-sdk
Download-URL: https://pypi.org/project/lfapi
Author: Joseph Masom
Author-email: joseph.masom@listenfirstmedia.com
License: MIT
Keywords: listenfirst api sdk
Classifier: Development Status :: 4 - Beta
Classifier: Intended Audience :: Developers
Classifier: License :: OSI Approved :: MIT License
Classifier: Programming Language :: Python :: 3
Classifier: Programming Language :: Python :: 3.8
Classifier: Programming Language :: Python :: 3.9
Classifier: Programming Language :: Python :: 3.10
Classifier: Programming Language :: Python :: 3.11
Requires-Python: >=3.8, <4
License-File: LICENSE.md
Requires-Dist: requests ~=2.31.0
